nonebot_plugin_questionmark/__init__.py
nonebot_plugin_questionmark/config.py
nonebot_plugin_questionmark-0.4.1.dist-info/LICENSE
nonebot_plugin_questionmark-0.4.1.dist-info/METADATA
nonebot_plugin_questionmark-0.4.1.dist-info/WHEEL
nonebot_plugin_questionmark-0.4.1.dist-info/top_level.txt
nonebot_plugin_questionmark-0.4.1.dist-info/RECORD
