Metadata-Version: 2.1
Name: nonebot-plugin-questionmark
Version: 0.4.1
Summary: NoneBot2 行为艺术插件, 有群友或私聊发送全是问号/感叹号的消息时, bot会自动把问号/感叹号方向翻转并发出来
Home-page: https://github.com/NumberSir/nonebot_plugin_questionmark
Author: Number_Sir
Author-email: Number_Sir@126.com
Keywords: pip,nonebot2,nonebot,nonebot_plugin
Platform: any
Classifier: Programming Language :: Python :: 3
Classifier: License :: OSI Approved :: MIT License
Classifier: Operating System :: OS Independent
Requires-Python: >=3.8
License-File: LICENSE
Requires-Dist: nonebot2 (>=2.0.0rc3)
